register/__init__.py
register/register.py
pico_register-0.1.0.dist-info/LICENSE
pico_register-0.1.0.dist-info/METADATA
pico_register-0.1.0.dist-info/WHEEL
pico_register-0.1.0.dist-info/top_level.txt
pico_register-0.1.0.dist-info/RECORD
