Metadata-Version: 2.1
Name: pico-register
Version: 0.1.0
Summary: Micropython library to interact with registers and individual bits of devices connected to SPI.
Home-page: https://github.com/cbraissant/lps22hh_pico_driver
Author: Chris Braissant
Author-email: chrisbraissant@gmail.com
License: MIT
Classifier: Development Status :: 3 - Alpha
Classifier: Operating System :: OS Independent
Classifier: License :: OSI Approved :: MIT License
Classifier: Intended Audience :: Developers
Classifier: Programming Language :: Python :: 3
Classifier: Programming Language :: Python :: 3.11
Classifier: Topic :: Software Development :: Embedded Systems
License-File: LICENSE
